image_tabular/__init__.py
image_tabular/_nbdev.py
image_tabular/core.py
image_tabular/dataset.py
image_tabular/metric.py
image_tabular/model.py
image_tabular-0.0.6.dist-info/LICENSE
image_tabular-0.0.6.dist-info/METADATA
image_tabular-0.0.6.dist-info/WHEEL
image_tabular-0.0.6.dist-info/entry_points.txt
image_tabular-0.0.6.dist-info/top_level.txt
image_tabular-0.0.6.dist-info/RECORD
