Metadata-Version: 2.1
Name: image-tabular
Version: 0.0.6
Summary: Integrate image and tabular data for deep learning
Home-page: https://github.com/naity/image_tabular/tree/master/
Author: Yuan Tian
Author-email: ytian@fredhutch.org
License: Apache Software License 2.0
Keywords: image tabular deeplearning
Platform: UNKNOWN
Classifier: Development Status :: 3 - Alpha
Classifier: Intended Audience :: Developers
Classifier: License :: OSI Approved :: Apache Software License
Classifier: Natural Language :: English
Classifier: Programming Language :: Python :: 3.6
Classifier: Programming Language :: Python :: 3.7
Classifier: Programming Language :: Python :: 3.8
Requires-Python: >=3.6
Requires-Dist: fastai
Requires-Dist: torch
Requires-Dist: torchvision
Requires-Dist: scikit-learn
